[
  {
    "keyword": "Single-Cell RNA Sequencing",
    "normalized_keyword": "single-cell rna sequencing",
    "growth_rate": Infinity,
    "momentum": 0.0,
    "degree": 0.0064516129032258064,
    "betweenness": 0.0,
    "pagerank": 0.01948877086195838,
    "occurrence_count": 2,
    "snapshot_date": "2026-04-15T05:07:29.854870"
  },
  {
    "keyword": "RNA Sequencing",
    "normalized_keyword": "rna sequencing",
    "growth_rate": Infinity,
    "momentum": 0.0,
    "degree": 0.0064516129032258064,
    "betweenness": 0.0,
    "pagerank": 0.01948877086195838,
    "occurrence_count": 2,
    "snapshot_date": "2026-04-15T05:07:29.854870"
  },
  {
    "keyword": "Sequencing and Machine",
    "normalized_keyword": "sequencing and machine",
    "growth_rate": Infinity,
    "momentum": 0.0,
    "degree": 0.0064516129032258064,
    "betweenness": 0.0,
    "pagerank": 0.01948877086195838,
    "occurrence_count": 2,
    "snapshot_date": "2026-04-15T05:07:29.854870"
  },
  {
    "keyword": "Machine Learning",
    "normalized_keyword": "machine learning",
    "growth_rate": Infinity,
    "momentum": 0.0,
    "degree": 0.0032258064516129032,
    "betweenness": 0.0,
    "pagerank": 0.01948877086195838,
    "occurrence_count": 2,
    "snapshot_date": "2026-04-15T05:07:29.854870"
  },
  {
    "keyword": "Learning to Identify",
    "normalized_keyword": "learning to identify",
    "growth_rate": Infinity,
    "momentum": 0.0,
    "degree": 0.0032258064516129032,
    "betweenness": 0.0,
    "pagerank": 0.01948877086195838,
    "occurrence_count": 2,
    "snapshot_date": "2026-04-15T05:07:29.854870"
  },
  {
    "keyword": "Automation",
    "normalized_keyword": "automation",
    "growth_rate": Infinity,
    "momentum": 0.0,
    "degree": 0.0,
    "betweenness": 0.0,
    "pagerank": 0.0029495298878764844,
    "occurrence_count": 1,
    "snapshot_date": "2026-04-15T05:07:29.854870"
  },
  {
    "keyword": "digital twin technologies",
    "normalized_keyword": "digital twin technologies",
    "growth_rate": Infinity,
    "momentum": 0.0,
    "degree": 0.0,
    "betweenness": 0.0,
    "pagerank": 0.0029495298878764844,
    "occurrence_count": 1,
    "snapshot_date": "2026-04-15T05:07:29.854870"
  },
  {
    "keyword": "innovation in healthcare",
    "normalized_keyword": "innovation in healthcare",
    "growth_rate": Infinity,
    "momentum": 0.0,
    "degree": 0.0,
    "betweenness": 0.0,
    "pagerank": 0.0029495298878764844,
    "occurrence_count": 1,
    "snapshot_date": "2026-04-15T05:07:29.854870"
  },
  {
    "keyword": "bio-printing and digital",
    "normalized_keyword": "bio-printing and digital",
    "growth_rate": Infinity,
    "momentum": 0.0,
    "degree": 0.0,
    "betweenness": 0.0,
    "pagerank": 0.0029495298878764844,
    "occurrence_count": 1,
    "snapshot_date": "2026-04-15T05:07:29.854870"
  },
  {
    "keyword": "personalized therapies.",
    "normalized_keyword": "personalized therapies.",
    "growth_rate": Infinity,
    "momentum": 0.0,
    "degree": 0.0,
    "betweenness": 0.0,
    "pagerank": 0.0029495298878764844,
    "occurrence_count": 1,
    "snapshot_date": "2026-04-15T05:07:29.854870"
  },
  {
    "keyword": "decade of innovation",
    "normalized_keyword": "decade of innovation",
    "growth_rate": Infinity,
    "momentum": 0.0,
    "degree": 0.0,
    "betweenness": 0.0,
    "pagerank": 0.0029495298878764844,
    "occurrence_count": 1,
    "snapshot_date": "2026-04-15T05:07:29.854870"
  },
  {
    "keyword": "digital twin",
    "normalized_keyword": "digital twin",
    "growth_rate": Infinity,
    "momentum": 0.0,
    "degree": 0.0,
    "betweenness": 0.0,
    "pagerank": 0.0029495298878764844,
    "occurrence_count": 1,
    "snapshot_date": "2026-04-15T05:07:29.854870"
  },
  {
    "keyword": "twin technologies",
    "normalized_keyword": "twin technologies",
    "growth_rate": Infinity,
    "momentum": 0.0,
    "degree": 0.0,
    "betweenness": 0.0,
    "pagerank": 0.0029495298878764844,
    "occurrence_count": 1,
    "snapshot_date": "2026-04-15T05:07:29.854870"
  },
  {
    "keyword": "technologies for personalized",
    "normalized_keyword": "technologies for personalized",
    "growth_rate": Infinity,
    "momentum": 0.0,
    "degree": 0.0,
    "betweenness": 0.0,
    "pagerank": 0.0029495298878764844,
    "occurrence_count": 1,
    "snapshot_date": "2026-04-15T05:07:29.854870"
  },
  {
    "keyword": "healthcare",
    "normalized_keyword": "healthcare",
    "growth_rate": Infinity,
    "momentum": 0.0,
    "degree": 0.0,
    "betweenness": 0.0,
    "pagerank": 0.0029495298878764844,
    "occurrence_count": 1,
    "snapshot_date": "2026-04-15T05:07:29.854870"
  },
  {
    "keyword": "Digital twin applications",
    "normalized_keyword": "digital twin applications",
    "growth_rate": Infinity,
    "momentum": 0.0,
    "degree": 0.0,
    "betweenness": 0.0,
    "pagerank": 0.0029495298878764844,
    "occurrence_count": 1,
    "snapshot_date": "2026-04-15T05:07:29.854870"
  },
  {
    "keyword": "Digital twin",
    "normalized_keyword": "digital twin",
    "growth_rate": Infinity,
    "momentum": 0.0,
    "degree": 0.0,
    "betweenness": 0.0,
    "pagerank": 0.0029495298878764844,
    "occurrence_count": 1,
    "snapshot_date": "2026-04-15T05:07:29.854870"
  },
  {
    "keyword": "living with disability.",
    "normalized_keyword": "living with disability.",
    "growth_rate": Infinity,
    "momentum": 0.0,
    "degree": 0.0,
    "betweenness": 0.0,
    "pagerank": 0.0029495298878764844,
    "occurrence_count": 1,
    "snapshot_date": "2026-04-15T05:07:29.854870"
  },
  {
    "keyword": "twin applications",
    "normalized_keyword": "twin applications",
    "growth_rate": Infinity,
    "momentum": 0.0,
    "degree": 0.0,
    "betweenness": 0.0,
    "pagerank": 0.0029495298878764844,
    "occurrence_count": 1,
    "snapshot_date": "2026-04-15T05:07:29.854870"
  },
  {
    "keyword": "applications in healthcare",
    "normalized_keyword": "applications in healthcare",
    "growth_rate": Infinity,
    "momentum": 0.0,
    "degree": 0.0,
    "betweenness": 0.0,
    "pagerank": 0.0029495298878764844,
    "occurrence_count": 1,
    "snapshot_date": "2026-04-15T05:07:29.854870"
  }
]